LICENSE
README.rst
setup.py
onefuse/__init__.py
onefuse/admin.py
onefuse/backups.py
onefuse/cloudbolt_admin.py
onefuse/exceptions.py
onefuse.egg-info/PKG-INFO
onefuse.egg-info/SOURCES.txt
onefuse.egg-info/dependency_links.txt
onefuse.egg-info/requires.txt
onefuse.egg-info/top_level.txt