Metadata-Version: 2.1
Name: onefuse
Version: 9.4.7.2
Summary: OneFuse upstream provider package for Python
Home-page: https://github.com/CloudBoltSoftware/onefuse-python-module
Author: Cloudbolt Software, Inc.
Author-email: support@cloudbolt.io
License: Mozilla Public License 2.0 (MPL 2.0)
Platform: UNKNOWN
Classifier: Development Status :: 5 - Production/Stable
Classifier: Intended Audience :: Information Technology
Classifier: License :: OSI Approved :: Mozilla Public License 2.0 (MPL 2.0)
Classifier: Operating System :: OS Independent
Classifier: Programming Language :: Python :: 3
Classifier: Programming Language :: Python :: 3.9
License-File: LICENSE
